kfin/__init__.py
kfin/_kfin.py
kfin/koreaexim/__init__.py
kfin/koreaexim/exchange_rate.py
kfin-0.0.3.dist-info/LICENSE
kfin-0.0.3.dist-info/METADATA
kfin-0.0.3.dist-info/WHEEL
kfin-0.0.3.dist-info/top_level.txt
kfin-0.0.3.dist-info/RECORD
